{
  "generated": "2026-07-13T23:43:51Z",
  "image": "stump",
  "tags": {
    "latest": {
      "app_version": "v0.1.5",
      "arch": "amd64",
      "generated": "2026-07-13T23:42:33Z",
      "packages": {
        "dotnet": [],
        "freebsd": [
          {
            "name": "FreeBSD-audit-lib",
            "version": "15.1"
          },
          {
            "name": "FreeBSD-blocklist",
            "version": "15.1"
          },
          {
            "name": "FreeBSD-bzip2-lib",
            "version": "15.1"
          },
          {
            "name": "FreeBSD-certctl",
            "version": "15.1"
          },
          {
            "name": "FreeBSD-clibs",
            "version": "15.1p1"
          },
          {
            "name": "FreeBSD-ctf-lib",
            "version": "15.1"
          },
          {
            "name": "FreeBSD-fetch",
            "version": "15.1"
          },
          {
            "name": "FreeBSD-kerberos-lib",
            "version": "15.1"
          },
          {
            "name": "FreeBSD-libarchive",
            "version": "15.1"
          },
          {
            "name": "FreeBSD-libbsdstat",
            "version": "15.1"
          },
          {
            "name": "FreeBSD-libcasper",
            "version": "15.1"
          },
          {
            "name": "FreeBSD-libexecinfo",
            "version": "15.1"
          },
          {
            "name": "FreeBSD-libldns",
            "version": "15.1"
          },
          {
            "name": "FreeBSD-libmagic",
            "version": "15.1"
          },
          {
            "name": "FreeBSD-libucl",
            "version": "15.1"
          },
          {
            "name": "FreeBSD-mtree",
            "version": "15.1"
          },
          {
            "name": "FreeBSD-ncurses-lib",
            "version": "15.1"
          },
          {
            "name": "FreeBSD-openssl",
            "version": "15.1"
          },
          {
            "name": "FreeBSD-openssl-lib",
            "version": "15.1"
          },
          {
            "name": "FreeBSD-pam-lib",
            "version": "15.1"
          },
          {
            "name": "FreeBSD-pkg-bootstrap",
            "version": "15.1"
          },
          {
            "name": "FreeBSD-rc",
            "version": "15.1"
          },
          {
            "name": "FreeBSD-runtime",
            "version": "15.1p1"
          },
          {
            "name": "FreeBSD-tcpd",
            "version": "15.1"
          },
          {
            "name": "FreeBSD-ufs-lib",
            "version": "15.1"
          },
          {
            "name": "FreeBSD-utilities",
            "version": "15.1p1"
          },
          {
            "name": "FreeBSD-xz-lib",
            "version": "15.1"
          },
          {
            "name": "FreeBSD-zfs-lib",
            "version": "15.1p1"
          },
          {
            "name": "FreeBSD-zlib",
            "version": "15.1"
          },
          {
            "name": "FreeBSD-zoneinfo",
            "version": "15.1"
          },
          {
            "name": "FreeBSD-zstd-lib",
            "version": "15.1"
          },
          {
            "name": "abseil",
            "version": "20250127.1_1"
          },
          {
            "name": "ca_root_nss",
            "version": "3.125"
          },
          {
            "name": "execline",
            "version": "2.9.8.1"
          },
          {
            "name": "icu",
            "version": "76.1,1"
          },
          {
            "name": "jbigkit",
            "version": "2.1_3"
          },
          {
            "name": "jpeg-turbo",
            "version": "3.1.4.1"
          },
          {
            "name": "jq",
            "version": "1.8.2"
          },
          {
            "name": "lcms2",
            "version": "2.19.1"
          },
          {
            "name": "lerc",
            "version": "4.1.0"
          },
          {
            "name": "libdeflate",
            "version": "1.25"
          },
          {
            "name": "libedit",
            "version": "3.1.20260512,1"
          },
          {
            "name": "liblz4",
            "version": "1.10.0_2,1"
          },
          {
            "name": "oniguruma",
            "version": "6.9.10"
          },
          {
            "name": "openjpeg",
            "version": "2.5.4_2"
          },
          {
            "name": "pdfium",
            "version": "7746"
          },
          {
            "name": "pkg",
            "version": "2.7.5"
          },
          {
            "name": "png",
            "version": "1.6.58"
          },
          {
            "name": "s6",
            "version": "2.14.0.1"
          },
          {
            "name": "skalibs",
            "version": "2.14.5.1"
          },
          {
            "name": "sqlite3",
            "version": "3.53.3,1"
          },
          {
            "name": "tiff",
            "version": "4.7.1_1"
          },
          {
            "name": "zstd",
            "version": "1.5.7_2"
          }
        ],
        "go": [],
        "java": [],
        "node": [],
        "php": [],
        "python": [],
        "ruby": [],
        "rust": []
      },
      "source": "upstream",
      "summary": {
        "dotnet": 0,
        "freebsd": 53,
        "go": 0,
        "java": 0,
        "node": 0,
        "php": 0,
        "python": 0,
        "ruby": 0,
        "rust": 0,
        "total": 53
      }
    }
  }
}
